gytmdl/__init__.py
gytmdl/__main__.py
gytmdl/cli.py
gytmdl/constants.py
gytmdl/custom_logger_formatter.py
gytmdl/downloader.py
gytmdl/enums.py
gytmdl/utils.py
gytmdl-2.1.6.dist-info/entry_points.txt
gytmdl-2.1.6.dist-info/WHEEL
gytmdl-2.1.6.dist-info/METADATA
gytmdl-2.1.6.dist-info/RECORD
