Metadata-Version: 2.4
Name: gytmdl
Version: 2.1.6
Summary: A command-line app for downloading YouTube Music songs with tags from YouTube Music.
Author: glomatico
Requires-Python: >=3.10
Requires-Dist: click
Requires-Dist: colorama
Requires-Dist: inquirerpy
Requires-Dist: mutagen
Requires-Dist: pillow
Requires-Dist: yt-dlp
Requires-Dist: ytmusicapi
Project-URL: repository, https://github.com/glomatico/gytmdl
